Workbook

Sheet Assumptions
A1: Assumptions
A2: Blue = edit these. Yellow = key pricing/cost levers to test.
A3: Pricing
A4: Price per student / year (₹) | B4: 120
A5: Payment processing fee (% of revenue) | B5: 0.02
A7: Fixed platform cost — per month
A8: Infra: EC2 + EBS + backups (₹/mo) | B8: 1600
A9: Tooling: monitoring, errors, email base (₹/mo) | B9: 800
A10: Fixed cost per month (₹) | B10: =SUM(B7:B8) -> 1600
A11: Fixed cost per year (₹) | B11: =B9*12 -> 9600
A13: Variable cost — per student / year
A14: Storage + email + egress per student/yr (₹) | B14: 15
A16: Per-college costs
A17: Onboarding — one-time (₹/college) | B17: 5000
A18: Support (₹/college/year) | B18: 6000

Sheet Colleges
A1: Colleges
A2: Type in blue cells. Row 5 is a worked example — overwrite or add colleges below it. Grey columns compute themselves.
A4: College | B4: Students | C4: Price/student/yr (₹) | D4: ARR (₹) | E4: Variable cost/yr | F4: Support/yr | G4: Gross profit/yr | H4: Margin %
A5: Demo Institute of Technology | B5: 2000 | C5: =Assumptions!$B$4 -> 120 | D5: =IF($B5="","",$B5*$C5) -> 240000 | E5: =IF($B5="","",$B5*Assumptions!$B$14) -> 30000 | F5: =IF($B5="","",Assumptions!$B$18) -> 6000 | G5: =IF($B5="","",$D5-$E5-$F5-$D5*Assumptions!$B$5) -> 199200 | H5: =IF($D5="","",IFERROR($G5/$D5,0)) -> 0.83
D6: =IF($B6="","",$B6*$C6) | E6: =IF($B6="","",$B6*Assumptions!$B$14) | F6: =IF($B6="","",Assumptions!$B$18) | G6: =IF($B6="","",$D6-$E6-$F6-$D6*Assumptions!$B$5) | H6: =IF($D6="","",IFERROR($G6/$D6,0))
D7: =IF($B7="","",$B7*$C7) | E7: =IF($B7="","",$B7*Assumptions!$B$14) | F7: =IF($B7="","",Assumptions!$B$18) | G7: =IF($B7="","",$D7-$E7-$F7-$D7*Assumptions!$B$5) | H7: =IF($D7="","",IFERROR($G7/$D7,0))
D8: =IF($B8="","",$B8*$C8) | E8: =IF($B8="","",$B8*Assumptions!$B$14) | F8: =IF($B8="","",Assumptions!$B$18) | G8: =IF($B8="","",$D8-$E8-$F8-$D8*Assumptions!$B$5) | H8: =IF($D8="","",IFERROR($G8/$D8,0))
D9: =IF($B9="","",$B9*$C9) | E9: =IF($B9="","",$B9*Assumptions!$B$14) | F9: =IF($B9="","",Assumptions!$B$18) | G9: =IF($B9="","",$D9-$E9-$F9-$D9*Assumptions!$B$5) | H9: =IF($D9="","",IFERROR($G9/$D9,0))
D10: =IF($B10="","",$B10*$C10) | E10: =IF($B10="","",$B10*Assumptions!$B$14) | F10: =IF($B10="","",Assumptions!$B$18) | G10: =IF($B10="","",$D10-$E10-$F10-$D10*Assumptions!$B$5) | H10: =IF($D10="","",IFERROR($G10/$D10,0))
D11: =IF($B11="","",$B11*$C11) | E11: =IF($B11="","",$B11*Assumptions!$B$14) | F11: =IF($B11="","",Assumptions!$B$18) | G11: =IF($B11="","",$D11-$E11-$F11-$D11*Assumptions!$B$5) | H11: =IF($D11="","",IFERROR($G11/$D11,0))
D12: =IF($B12="","",$B12*$C12) | E12: =IF($B12="","",$B12*Assumptions!$B$14) | F12: =IF($B12="","",Assumptions!$B$18) | G12: =IF($B12="","",$D12-$E12-$F12-$D12*Assumptions!$B$5) | H12: =IF($D12="","",IFERROR($G12/$D12,0))
D13: =IF($B13="","",$B13*$C13) | E13: =IF($B13="","",$B13*Assumptions!$B$14) | F13: =IF($B13="","",Assumptions!$B$18) | G13: =IF($B13="","",$D13-$E13-$F13-$D13*Assumptions!$B$5) | H13: =IF($D13="","",IFERROR($G13/$D13,0))
D14: =IF($B14="","",$B14*$C14) | E14: =IF($B14="","",$B14*Assumptions!$B$14) | F14: =IF($B14="","",Assumptions!$B$18) | G14: =IF($B14="","",$D14-$E14-$F14-$D14*Assumptions!$B$5) | H14: =IF($D14="","",IFERROR($G14/$D14,0))
D15: =IF($B15="","",$B15*$C15) | E15: =IF($B15="","",$B15*Assumptions!$B$14) | F15: =IF($B15="","",Assumptions!$B$18) | G15: =IF($B15="","",$D15-$E15-$F15-$D15*Assumptions!$B$5) | H15: =IF($D15="","",IFERROR($G15/$D15,0))
D16: =IF($B16="","",$B16*$C16) | E16: =IF($B16="","",$B16*Assumptions!$B$14) | F16: =IF($B16="","",Assumptions!$B$18) | G16: =IF($B16="","",$D16-$E16-$F16-$D16*Assumptions!$B$5) | H16: =IF($D16="","",IFERROR($G16/$D16,0))
D17: =IF($B17="","",$B17*$C17) | E17: =IF($B17="","",$B17*Assumptions!$B$14) | F17: =IF($B17="","",Assumptions!$B$18) | G17: =IF($B17="","",$D17-$E17-$F17-$D17*Assumptions!$B$5) | H17: =IF($D17="","",IFERROR($G17/$D17,0))
... D34: =IF($B34="","",$B34*$C34) | E34: =IF($B34="","",$B34*Assumptions!$B$14) | F34: =IF($B34="","",Assumptions!$B$18) | G34: =IF($B34="","",$D34-$E34-$F34-$D34*Assumptions!$B$5) | H34: =IF($D34="","",IFERROR($G34/$D34,0))
A36: TOTAL | B36: =SUM(B5:B34) -> 2000 | D36: =SUM(D5:D34) -> 240000 | E36: =SUM(E5:E34) -> 30000 | F36: =SUM(F5:F34) -> 6000 | G36: =SUM(G5:G34) -> 199200 | H36: =IFERROR(G36/D36,0) -> 0.83

Sheet Summary
A1: Summary
A2: Reads from Colleges + Assumptions. Blue cell = your available cash/credit.
A4: Colleges (paying) | B4: =SUMPRODUCT(--(Colleges!B5:B34<>"")) -> 1
A5: Total students | B5: =Colleges!B36 -> 2000
A7: ARR — annual recurring revenue (₹) | B7: =Colleges!D36 -> 240000
A8: MRR — monthly recurring revenue (₹) | B8: =B7/12 -> 20000
A10: Variable cost / yr (₹) | B10: =Colleges!E36 -> 30000
A11: Support cost / yr (₹) | B11: =Colleges!F36 -> 6000
A12: Fixed platform cost / yr (₹) | B12: =Assumptions!B11 -> 9600
A13: Total cost to serve / yr (₹) | B13: =B10+B11+B12 -> 45600
A15: Gross profit / yr (₹) | B15: =Colleges!G36-B12 -> 189600
A16: Blended gross margin | B16: =IFERROR(B15/B7,0) -> 0.79
A17: Cost to serve per student / yr (₹) | B17: =IFERROR(B13/B5,0) -> 22.8
A19: Cash / AWS credit available (₹) | B19: 8000
A20: Net monthly result (₹) [+ = profit] | B20: =B15/12 -> 15800
A21: Runway if unprofitable (months) | B21: =IF(B20>=0,"profitable",IFERROR(-B19/B20,0)) -> profitable
